KyInter/KyCore.py
KyInter/KySetups.py
KyInter/KyWidgets.py
KyInter/__init__.py
KyInter/tksvg/__init__.py
KyInter/tksvg/libtksvg.dll
KyInter/tksvg/pkgIndex.tcl
kyinter-1.0.1.dist-info/licenses/LICENSE
kyinter-1.0.1.dist-info/METADATA
kyinter-1.0.1.dist-info/WHEEL
kyinter-1.0.1.dist-info/top_level.txt
kyinter-1.0.1.dist-info/RECORD
