Metadata-Version: 2.4
Name: KyInter
Version: 1.0.1
Summary: A library for creating personalization window.
Home-page: https://github.com/JimmyJimmy666/KyInter
Author: bzNAK
Classifier: Programming Language :: Python :: 3
Classifier: License :: OSI Approved :: MIT License
Classifier: Operating System :: OS Independent
Requires-Python: >=3.6
License-File: LICENSE
Dynamic: author
Dynamic: classifier
Dynamic: description
Dynamic: description-content-type
Dynamic: home-page
Dynamic: license-file
Dynamic: requires-python
Dynamic: summary
